 RESUME                   0

  1           LOAD_CONST               0 (0)
              LOAD_CONST               1 (('MongoClient',))
              IMPORT_NAME              0 (pymongo)
              IMPORT_FROM              1 (MongoClient)
              STORE_NAME               1 (MongoClient)
              POP_TOP

  2           LOAD_CONST               0 (0)
              LOAD_CONST               2 (('ObjectId',))
              IMPORT_NAME              2 (bson.objectid)
              IMPORT_FROM              3 (ObjectId)
              STORE_NAME               3 (ObjectId)
              POP_TOP

  3           LOAD_CONST               0 (0)
              LOAD_CONST               3 (None)
              IMPORT_NAME              4 (urllib.parse)
              STORE_NAME               5 (urllib)

  7           LOAD_BUILD_CLASS
              PUSH_NULL
              LOAD_CONST               4 (<code object AnimalShelter at 0x59186b46bdc0, file "example.py", line 7>)
              MAKE_FUNCTION
              LOAD_CONST               5 ('AnimalShelter')
              LOAD_NAME                6 (object)
              CALL                     3
              STORE_NAME               7 (AnimalShelter)
              RETURN_CONST             3 (None)

Disassembly of <code object AnimalShelter at 0x59186b46bdc0, file "example.py", line 7>:
  7           RESUME                   0
              LOAD_NAME                0 (__name__)
              STORE_NAME               1 (__module__)
              LOAD_CONST               0 ('AnimalShelter')
              STORE_NAME               2 (__qualname__)
              LOAD_CONST               1 (7)
              STORE_NAME               3 (__firstlineno__)

 10           LOAD_CONST               2 (0)
              STORE_NAME               4 (records_updated)

 11           LOAD_CONST               2 (0)
              STORE_NAME               5 (records_matched)

 12           LOAD_CONST               2 (0)
              STORE_NAME               6 (records_deleted)

 16           LOAD_CONST              11 (('merlina2000',))
              LOAD_CONST               3 (<code object __init__ at 0x59186b46f9d0, file "example.py", line 16>)
              MAKE_FUNCTION
              SET_FUNCTION_ATTRIBUTE   1 (defaults)
              STORE_NAME               7 (__init__)

 28           LOAD_CONST               4 (<code object createRecord at 0x59186b3eba60, file "example.py", line 28>)
              MAKE_FUNCTION
              STORE_NAME               8 (createRecord)

 41           LOAD_CONST               5 (<code object getRecordId at 0x59186b477470, file "example.py", line 41>)
              MAKE_FUNCTION
              STORE_NAME               9 (getRecordId)

 51           LOAD_CONST               6 (<code object getRecordCriteria at 0x59186b416e30, file "example.py", line 51>)
              MAKE_FUNCTION
              STORE_NAME              10 (getRecordCriteria)

 61           LOAD_CONST               7 (<code object updateRecord at 0x59186b46d6c0, file "example.py", line 61>)
              MAKE_FUNCTION
              STORE_NAME              11 (updateRecord)

 73           LOAD_CONST               8 (<code object deleteRecord at 0x59186b46c050, file "example.py", line 73>)
              MAKE_FUNCTION
              STORE_NAME              12 (deleteRecord)
              LOAD_CONST               9 (('client', 'dataBase', 'records_deleted', 'records_matched', 'records_updated'))
              STORE_NAME              13 (__static_attributes__)
              RETURN_CONST            10 (None)

Disassembly of <code object __init__ at 0x59186b46f9d0, file "example.py", line 16>:
 16           RESUME                   0

 19           LOAD_GLOBAL              0 (urllib)
              LOAD_ATTR                2 (parse)
              LOAD_ATTR                5 (quote_plus + NULL|self)
              LOAD_FAST                2 (_userName)
              CALL                     1
              STORE_FAST               3 (userName)

 20           LOAD_GLOBAL              0 (urllib)
              LOAD_ATTR                2 (parse)
              LOAD_ATTR                5 (quote_plus + NULL|self)
              LOAD_FAST                1 (_password)
              CALL                     1
              STORE_FAST               4 (password)

 22           LOAD_GLOBAL              7 (MongoClient + NULL)
              LOAD_CONST               1 ('mongodb://')
              LOAD_FAST                3 (userName)
              CONVERT_VALUE            1 (str)
              FORMAT_SIMPLE
              LOAD_CONST               2 (':')
              LOAD_FAST                4 (password)
              CONVERT_VALUE            1 (str)
              FORMAT_SIMPLE
              LOAD_CONST               3 ('@localhost:32256/?authSource=AAC2')
              BUILD_STRING             5
              CALL                     1
              LOAD_FAST                0 (self)
              STORE_ATTR               4 (client)

 23           LOAD_FAST                0 (self)
              LOAD_ATTR                8 (client)
              LOAD_CONST               4 ('AAC2')
              BINARY_SUBSCR
              LOAD_FAST                0 (self)
              STORE_ATTR               5 (dataBase)
              RETURN_CONST             0 (None)

Disassembly of <code object createRecord at 0x59186b3eba60, file "example.py", line 28>:
 28           RESUME                   0

 29           LOAD_FAST                1 (data)
              TO_BOOL
              POP_JUMP_IF_FALSE       58 (to L2)

 30           LOAD_FAST                0 (self)
              LOAD_ATTR                0 (dataBase)
              LOAD_ATTR                2 (animals)
              LOAD_ATTR                5 (insert_one + NULL|self)
              LOAD_FAST                1 (data)
              CALL                     1
              STORE_FAST               2 (_insertValid)

 32           LOAD_FAST                2 (_insertValid)
              LOAD_ATTR                6 (acknowledged)
              TO_BOOL
              POP_JUMP_IF_FALSE        2 (to L1)
              LOAD_CONST               1 (True)
              RETURN_VALUE
      L1:     LOAD_CONST               2 (False)
              RETURN_VALUE

 35   L2:     LOAD_GLOBAL              9 (Exception + NULL)
              LOAD_CONST               3 ('No document to save. Data is empty.')
              CALL                     1
              RAISE_VARARGS            1

Disassembly of <code object getRecordId at 0x59186b477470, file "example.py", line 41>:
 41           RESUME                   0

 42           LOAD_FAST                0 (self)
              LOAD_ATTR                0 (dataBase)
              LOAD_ATTR                3 (find_one + NULL|self)
              LOAD_CONST               1 ('_id')
              LOAD_GLOBAL              5 (ObjectId + NULL)
              LOAD_FAST                1 (postId)
              CALL                     1
              BUILD_MAP                1
              CALL                     1
              STORE_FAST               2 (_data)

 44           LOAD_FAST                2 (_data)
              RETURN_VALUE

Disassembly of <code object getRecordCriteria at 0x59186b416e30, file "example.py", line 51>:
 51           RESUME                   0

 52           LOAD_FAST                1 (criteria)
              TO_BOOL
              POP_JUMP_IF_FALSE       42 (to L1)

 53           LOAD_FAST                0 (self)
              LOAD_ATTR                0 (dataBase)
              LOAD_ATTR                2 (animals)
              LOAD_ATTR                5 (find + NULL|self)
              LOAD_FAST                1 (criteria)
              LOAD_CONST               1 ('_id')
              LOAD_CONST               2 (0)
              BUILD_MAP                1
              CALL                     2
              STORE_FAST               2 (_data)

 58           LOAD_FAST                2 (_data)
              RETURN_VALUE

 56   L1:     LOAD_FAST                0 (self)
              LOAD_ATTR                0 (dataBase)
              LOAD_ATTR                2 (animals)
              LOAD_ATTR                5 (find + NULL|self)
              BUILD_MAP                0
              LOAD_CONST               1 ('_id')
              LOAD_CONST               2 (0)
              BUILD_MAP                1
              CALL                     2
              STORE_FAST               2 (_data)

 58           LOAD_FAST                2 (_data)
              RETURN_VALUE

Disassembly of <code object updateRecord at 0x59186b46d6c0, file "example.py", line 61>:
 61           RESUME                   0

 62           LOAD_FAST                1 (query)
              TO_BOOL
              POP_JUMP_IF_TRUE        11 (to L1)

 63           LOAD_GLOBAL              1 (Exception + NULL)
              LOAD_CONST               1 ('No search criteria is present.')
              CALL                     1
              RAISE_VARARGS            1

 64   L1:     LOAD_FAST                2 (newValue)
              TO_BOOL
              POP_JUMP_IF_TRUE        11 (to L2)

 65           LOAD_GLOBAL              1 (Exception + NULL)
              LOAD_CONST               2 ('No update value is present.')
              CALL                     1
              RAISE_VARARGS            1

 67   L2:     LOAD_FAST                0 (self)
              LOAD_ATTR                2 (dataBase)
              LOAD_ATTR                4 (animals)
              LOAD_ATTR                7 (update_many + NULL|self)
              LOAD_FAST                1 (query)
              LOAD_CONST               3 ('$set')
              LOAD_FAST                2 (newValue)
              BUILD_MAP                1
              CALL                     2
              STORE_FAST               3 (_updateValid)

 68           LOAD_FAST                3 (_updateValid)
              LOAD_ATTR                8 (modified_count)
              LOAD_FAST                0 (self)
              STORE_ATTR               5 (records_updated)

 69           LOAD_FAST                3 (_updateValid)
              LOAD_ATTR               12 (matched_count)
              LOAD_FAST                0 (self)
              STORE_ATTR               7 (records_matched)

 71           LOAD_FAST                3 (_updateValid)
              LOAD_ATTR                8 (modified_count)
              LOAD_CONST               4 (0)
              COMPARE_OP             148 (bool(>))
              POP_JUMP_IF_FALSE        2 (to L3)
              LOAD_CONST               5 (True)
              RETURN_VALUE
      L3:     LOAD_CONST               6 (False)
              RETURN_VALUE

Disassembly of <code object deleteRecord at 0x59186b46c050, file "example.py", line 73>:
 73           RESUME                   0

 74           LOAD_FAST                1 (query)
              TO_BOOL
              POP_JUMP_IF_TRUE        11 (to L1)

 75           LOAD_GLOBAL              1 (Exception + NULL)
              LOAD_CONST               1 ('No search criteria is present.')
              CALL                     1
              RAISE_VARARGS            1

 78   L1:     LOAD_FAST                0 (self)
              LOAD_ATTR                2 (dataBase)
              LOAD_ATTR                4 (animals)
              LOAD_ATTR                7 (delete_many + NULL|self)
              LOAD_FAST                1 (query)
              CALL                     1
              STORE_FAST               2 (_deleteValid)

 79           LOAD_FAST                2 (_deleteValid)
              LOAD_ATTR                8 (deleted_count)
              LOAD_FAST                0 (self)
              STORE_ATTR               5 (records_deleted)

 81           LOAD_FAST                2 (_deleteValid)
              LOAD_ATTR                8 (deleted_count)
              LOAD_CONST               2 (0)
              COMPARE_OP             148 (bool(>))
              POP_JUMP_IF_FALSE        2 (to L2)
              LOAD_CONST               3 (True)
              RETURN_VALUE
      L2:     LOAD_CONST               4 (False)
              RETURN_VALUE